conv/__init__.py
conv/conv.py
conv/tests/__init__.py
conv/tests/test_convolved_1d.py
conv/tests/test_convolved_2d.py
conv-0.1.dist-info/METADATA
conv-0.1.dist-info/RECORD
conv-0.1.dist-info/WHEEL
conv-0.1.dist-info/top_level.txt
