Metadata-Version: 2.1
Name: conv
Version: 0.1
Summary: A lightweight library to do for-loop-styled convolution passes on your iterable objects (e.g.: on a list).
Home-page: https://github.com/guillaume-chevalier/python-conv-lib
Author: Guillaume Chevalier
Author-email: guillaume-chevalier@outlook.com
License: MIT
Download-URL: https://github.com/guillaume-chevalier/python-conv-lib/tarball/0.1
Keywords: convolution conv conv1d conv2d convolve convolved
Platform: UNKNOWN
Classifier: Development Status :: 3 - Alpha
Classifier: Intended Audience :: Developers
Classifier: Intended Audience :: Science/Research
Classifier: Intended Audience :: Information Technology
Classifier: License :: OSI Approved :: MIT License
Classifier: Natural Language :: English
Classifier: Operating System :: OS Independent
Classifier: Programming Language :: Python :: 3
Classifier: Programming Language :: Python :: 3.6
Classifier: Topic :: Scientific/Engineering :: Artificial Intelligence
Classifier: Topic :: Scientific/Engineering :: Mathematics
Classifier: Topic :: Software Development :: Libraries
Classifier: Topic :: Software Development :: Libraries :: Python Modules
Classifier: Topic :: Utilities
